graphvelo/__init__.py
graphvelo/gam.py
graphvelo/graph_velocity.py
graphvelo/kernel_density_smooth.py
graphvelo/metrics.py
graphvelo/mo.py
graphvelo/plot.py
graphvelo/tangent_space.py
graphvelo/utils.py
graphvelo-0.1.11.dist-info/licenses/LICENSE
graphvelo-0.1.11.dist-info/WHEEL
graphvelo-0.1.11.dist-info/METADATA
graphvelo-0.1.11.dist-info/RECORD
