Metadata-Version: 2.4
Name: GraphVelo
Version: 0.1.11
Summary: Inferring manifold-constrained velocity and transforming vectors across representations
Author-email: Yuhao Chen <yuhaoc@zju.edu.cn>
Requires-Python: >=3.8
Classifier: Development Status :: 4 - Beta
Classifier: Intended Audience :: Science/Research
Classifier: Natural Language :: English
Classifier: License :: OSI Approved :: BSD License
Classifier: Topic :: Scientific/Engineering :: Bio-Informatics
License-File: LICENSE
Requires-Dist: tqdm
Requires-Dist: numpy>=1.24.3,<1.25
Requires-Dist: scipy>=1.10.1,<1.11
Requires-Dist: pygam>=0.9.1,<1.0
Requires-Dist: joblib
Requires-Dist: pandas>=2.0.3,<2.1.0
Requires-Dist: scikit-learn>=1.3.2,<1.4
Requires-Dist: anndata
Requires-Dist: scanpy>=1.9.8
Requires-Dist: matplotlib>=3.7.5,<4.0.0
Requires-Dist: seaborn>=0.13.2
Requires-Dist: plotly
Requires-Dist: sphinx ; extra == "docs"
Requires-Dist: sphinx_rtd_theme ; extra == "docs"
Requires-Dist: nbsphinx ; extra == "docs"
Requires-Dist: sphinx_autodoc_typehints ; extra == "docs"
Requires-Dist: sphinxcontrib-bibtex ; extra == "docs"
Requires-Dist: sphinx-gallery ; extra == "docs"
Requires-Dist: furo ; extra == "docs"
Requires-Dist: GitPython ; extra == "docs"
Requires-Dist: pytest ; extra == "testing"
Requires-Dist: pytest-cov ; extra == "testing"
Project-URL: documentation, https://graphvelo.readthedocs.io/en/latest/
Project-URL: homepage, https://github.com/xing-lab-pitt/GraphVelo
Project-URL: repository, https://github.com/xing-lab-pitt/GraphVelo
Provides-Extra: docs
Provides-Extra: testing
